vetting_python/__init__.py
vetting_python/cli.py
vetting_python/py.typed
vetting_python/config/__init__.py
vetting_python/config/builder.py
vetting_python/config/settings.py
vetting_python/core/__init__.py
vetting_python/core/framework.py
vetting_python/core/models.py
vetting_python/examples/__init__.py
vetting_python/examples/advanced_usage.py
vetting_python/examples/basic_usage.py
vetting_python/examples/integration_patterns.py
vetting_python/providers/__init__.py
vetting_python/providers/claude_provider.py
vetting_python/providers/gemini_provider.py
vetting_python/providers/openai_provider.py
vetting_python/utils/__init__.py
vetting_python/utils/cost_tracker.py
vetting_python/utils/message_utils.py
vetting_python/utils/validation.py
vetting_python-0.1.0.dist-info/licenses/LICENSE
vetting_python-0.1.0.dist-info/METADATA
vetting_python-0.1.0.dist-info/WHEEL
vetting_python-0.1.0.dist-info/entry_points.txt
vetting_python-0.1.0.dist-info/top_level.txt
vetting_python-0.1.0.dist-info/RECORD
