Metadata-Version: 2.4
Name: vetting-python
Version: 0.1.0
Summary: A Python implementation of the VETTING (Verification and Evaluation Tool for Targeting Invalid Narrative Generation) framework for LLM safety and educational applications
Author-email: VETTING Research Team <hli3@ufl.edu>
License: MIT License
Project-URL: Homepage, https://github.com/hichipli/vetting-python
Project-URL: Documentation, https://github.com/hichipli/vetting-python#readme
Project-URL: Repository, https://github.com/hichipli/vetting-python.git
Project-URL: Issues, https://github.com/hichipli/vetting-python/issues
Project-URL: Changelog, https://github.com/hichipli/vetting-python/blob/main/CHANGELOG.md
Keywords: llm,ai-safety,education,chatbot,verification,dual-llm,prompt-engineering,educational-technology,machine-learning,natural-language-processing
Classifier: Development Status :: 4 - Beta
Classifier: Intended Audience :: Developers
Classifier: Intended Audience :: Education
Classifier: Intended Audience :: Science/Research
Classifier: License :: OSI Approved :: MIT License
Classifier: Operating System :: OS Independent
Classifier: Programming Language :: Python :: 3
Classifier: Programming Language :: Python :: 3.8
Classifier: Programming Language :: Python :: 3.9
Classifier: Programming Language :: Python :: 3.10
Classifier: Programming Language :: Python :: 3.11
Classifier: Programming Language :: Python :: 3.12
Classifier: Topic :: Scientific/Engineering :: Artificial Intelligence
Classifier: Topic :: Education
Classifier: Topic :: Software Development :: Libraries :: Python Modules
Classifier: Topic :: Internet :: WWW/HTTP :: Dynamic Content
Classifier: Typing :: Typed
Requires-Python: >=3.8
License-File: LICENSE
Requires-Dist: aiohttp>=3.8.0
Requires-Dist: dataclasses-json>=0.5.7
Requires-Dist: pydantic>=1.10.0
Requires-Dist: typing-extensions>=4.0.0
Provides-Extra: yaml
Requires-Dist: PyYAML>=6.0; extra == "yaml"
Provides-Extra: dev
Requires-Dist: pytest>=7.0.0; extra == "dev"
Requires-Dist: pytest-asyncio>=0.21.0; extra == "dev"
Requires-Dist: pytest-cov>=4.0.0; extra == "dev"
Requires-Dist: black>=23.0.0; extra == "dev"
Requires-Dist: isort>=5.12.0; extra == "dev"
Requires-Dist: mypy>=1.0.0; extra == "dev"
Requires-Dist: pre-commit>=3.0.0; extra == "dev"
Requires-Dist: build>=0.10.0; extra == "dev"
Requires-Dist: twine>=4.0.0; extra == "dev"
Provides-Extra: docs
Requires-Dist: sphinx>=5.0.0; extra == "docs"
Requires-Dist: sphinx-rtd-theme>=1.2.0; extra == "docs"
Requires-Dist: myst-parser>=1.0.0; extra == "docs"
Provides-Extra: all
Requires-Dist: vetting-python[dev,docs,yaml]; extra == "all"
Dynamic: license-file
